NetworkWrapper/__init__.py
NetworkWrapper/NetworkWrapper.py
nn_wrapper-1.0.5.dist-info/LICENSE
nn_wrapper-1.0.5.dist-info/METADATA
nn_wrapper-1.0.5.dist-info/WHEEL
nn_wrapper-1.0.5.dist-info/RECORD
