Metadata-Version: 2.1
Name: nn-wrapper
Version: 1.0.5
Summary: A wrapper class for neural networks that makes working with them easier.
Home-page: https://github.com/JohnConnor123/NetworkWrapper
Author: JohnConnor123
Author-email: ivan.eudokimoff2014@gmail.com
Requires-Python: >=3.8
Classifier: Programming Language :: Python :: 3
Classifier: Programming Language :: Python :: 3.8
Classifier: Programming Language :: Python :: 3.9
Classifier: Programming Language :: Python :: 3.10
Classifier: Programming Language :: Python :: 3.11
Classifier: Programming Language :: Python :: 3.12
Requires-Dist: matplotlib (>=3.8.0)
Requires-Dist: numpy (>=1.24.2)
Requires-Dist: pandas (>=2.0.0)
Requires-Dist: scikit-learn (>=1.3.0)
Requires-Dist: seaborn (>=0.12.2)
Requires-Dist: torch (>=2.1.0)
Requires-Dist: torchaudio (>=2.1.0)
Requires-Dist: torchvision (>=0.16.0)
Requires-Dist: tqdm (>=4.66.1)
Project-URL: Repository, https://github.com/JohnConnor123/NetworkWrapper
